{
  "resolvedId": "virtual:nuxt:/mnt/1c4c2374-6f70-425b-ab4c-d1db6332863a/carlos/project/2024/CQM/.nuxt/router.options.mjs",
  "transforms": [
    {
      "name": "virtual",
      "result": "import routerOptions0 from \"/mnt/1c4c2374-6f70-425b-ab4c-d1db6332863a/carlos/project/2024/CQM/node_modules/nuxt/dist/pages/runtime/router.options\";\nconst configRouterOptions = {\n  hashMode: false,\n  scrollBehaviorType: \"auto\"\n}\nexport default {\n...configRouterOptions,\n...routerOptions0,\n}",
      "start": 1709717377630,
      "end": 1709717377630,
      "sourcemaps": null
    },
    {
      "name": "nuxt:layer-aliasing",
      "start": 1709717377630,
      "end": 1709717377630,
      "order": "pre"
    },
    {
      "name": "nuxt:server-devonly:transform",
      "start": 1709717377630,
      "end": 1709717377630,
      "order": "pre"
    },
    {
      "name": "nuxt:client-fallback-auto-id",
      "start": 1709717377630,
      "end": 1709717377630,
      "order": "pre"
    },
    {
      "name": "vite:css",
      "start": 1709717377630,
      "end": 1709717377630,
      "order": "normal"
    },
    {
      "name": "vite:esbuild",
      "start": 1709717377630,
      "end": 1709717377630,
      "order": "normal"
    },
    {
      "name": "vite:json",
      "start": 1709717377630,
      "end": 1709717377630,
      "order": "normal"
    },
    {
      "name": "vite:worker",
      "start": 1709717377631,
      "end": 1709717377631,
      "order": "normal"
    },
    {
      "name": "vite:vue",
      "start": 1709717377631,
      "end": 1709717377631,
      "order": "normal"
    },
    {
      "name": "vite:vue-jsx",
      "start": 1709717377631,
      "end": 1709717377631,
      "order": "normal"
    },
    {
      "name": "replace",
      "start": 1709717377631,
      "end": 1709717377631,
      "order": "normal"
    },
    {
      "name": "nuxt:remove-plugin-metadata",
      "start": 1709717377632,
      "end": 1709717377632,
      "order": "normal"
    },
    {
      "name": "nuxt:chunk-error",
      "start": 1709717377632,
      "end": 1709717377632,
      "order": "normal"
    },
    {
      "name": "nuxt:components:imports",
      "start": 1709717377632,
      "end": 1709717377632,
      "order": "normal"
    },
    {
      "name": "replace",
      "start": 1709717377685,
      "end": 1709717377685,
      "order": "normal"
    },
    {
      "name": "ssr-styles",
      "start": 1709717377686,
      "end": 1709717377686,
      "order": "normal"
    },
    {
      "name": "vite:define",
      "start": 1709717377687,
      "end": 1709717377687,
      "order": "normal"
    },
    {
      "name": "vite:css-post",
      "start": 1709717377687,
      "end": 1709717377687,
      "order": "normal"
    },
    {
      "name": "vite:build-html",
      "start": 1709717377713,
      "end": 1709717377713,
      "order": "normal"
    },
    {
      "name": "vite:worker-import-meta-url",
      "start": 1709717377724,
      "end": 1709717377724,
      "order": "normal"
    },
    {
      "name": "vite:asset-import-meta-url",
      "start": 1709717377730,
      "end": 1709717377730,
      "order": "normal"
    },
    {
      "name": "commonjs",
      "start": 1709717377730,
      "end": 1709717377730,
      "order": "normal"
    },
    {
      "name": "vite:dynamic-import-vars",
      "start": 1709717377730,
      "end": 1709717377730,
      "order": "normal"
    },
    {
      "name": "vite:import-glob",
      "start": 1709717377731,
      "end": 1709717377731,
      "order": "normal"
    },
    {
      "name": "nuxt:composable-keys",
      "start": 1709717377731,
      "end": 1709717377731,
      "order": "post"
    },
    {
      "name": "nuxt:imports-transform",
      "start": 1709717377731,
      "end": 1709717377758,
      "order": "post"
    },
    {
      "name": "unctx:transform",
      "start": 1709717377759,
      "end": 1709717377759,
      "order": "post"
    },
    {
      "name": "nuxt:pages-macros-transform",
      "start": 1709717377851,
      "end": 1709717377851,
      "order": "post"
    },
    {
      "name": "nuxt:runtime-paths-dep",
      "start": 1709717377877,
      "end": 1709717377878,
      "order": "post"
    },
    {
      "name": "nuxt:route-injection-plugin",
      "start": 1709717377882,
      "end": 1709717377882,
      "order": "post"
    },
    {
      "name": "nuxt:components-loader",
      "start": 1709717377883,
      "end": 1709717377883,
      "order": "post"
    },
    {
      "name": "nuxt:tree-shake-composables:transform",
      "start": 1709717377910,
      "end": 1709717377919,
      "order": "post"
    },
    {
      "name": "vite:build-import-analysis",
      "start": 1709717377939,
      "end": 1709717377939,
      "order": "normal"
    },
    {
      "name": "vite:reporter",
      "start": 1709717377960,
      "end": 1709717377960,
      "order": "normal"
    }
  ]
}
